huez/__init__.py
huez/cli.py
huez/color_correction.py
huez/config.py
huez/core.py
huez/preview.py
huez/adapters/__init__.py
huez/adapters/altair.py
huez/adapters/base.py
huez/adapters/bokeh.py
huez/adapters/geopandas.py
huez/adapters/holoviews.py
huez/adapters/hvplot.py
huez/adapters/mpl.py
huez/adapters/plotly.py
huez/adapters/plotnine.py
huez/adapters/pyecharts.py
huez/adapters/pyvista.py
huez/adapters/seaborn.py
huez/data/adapters_registry.yaml
huez/data/defaults.py
huez/data/defaults.yaml
huez/quality/__init__.py
huez/quality/checks.py
huez/quality/lint.py
huez/registry/__init__.py
huez/registry/journals.py
huez/registry/palettes.py
huez-0.0.3.dist-info/licenses/LICENSE
huez-0.0.3.dist-info/METADATA
huez-0.0.3.dist-info/WHEEL
huez-0.0.3.dist-info/top_level.txt
huez-0.0.3.dist-info/RECORD
