Metadata-Version: 2.4
Name: huez
Version: 0.0.3
Summary: A unified color scheme solution for Python visualization
Author-email: Ang <ang@hezhiang.com>
Maintainer-email: Ang <ang@hezhiang.com>
License: MIT
Project-URL: Homepage, https://github.com/hzacode/huez
Project-URL: Repository, https://github.com/hzacode/huez
Project-URL: Issues, https://github.com/hzacode/huez/issues
Keywords: visualization,color,scheme,matplotlib,seaborn,plotly,altair,plotnine
Classifier: Development Status :: 3 - Alpha
Classifier: Intended Audience :: Developers
Classifier: License :: OSI Approved :: MIT License
Classifier: Operating System :: OS Independent
Classifier: Programming Language :: Python :: 3
Classifier: Programming Language :: Python :: 3.7
Classifier: Programming Language :: Python :: 3.8
Classifier: Programming Language :: Python :: 3.9
Classifier: Programming Language :: Python :: 3.10
Classifier: Programming Language :: Python :: 3.11
Classifier: Topic :: Software Development :: Libraries :: Python Modules
Requires-Python: >=3.7
License-File: LICENSE
Requires-Dist: PyYAML>=6.0
Requires-Dist: click>=8.0.0
Provides-Extra: matplotlib
Requires-Dist: matplotlib>=3.5.0; extra == "matplotlib"
Provides-Extra: seaborn
Requires-Dist: seaborn>=0.11.0; extra == "seaborn"
Provides-Extra: plotly
Requires-Dist: plotly>=5.0.0; extra == "plotly"
Provides-Extra: altair
Requires-Dist: altair>=4.2.0; extra == "altair"
Provides-Extra: plotnine
Requires-Dist: plotnine>=0.8.0; extra == "plotnine"
Provides-Extra: all
Requires-Dist: matplotlib>=3.5.0; extra == "all"
Requires-Dist: seaborn>=0.11.0; extra == "all"
Requires-Dist: plotly>=5.0.0; extra == "all"
Requires-Dist: altair>=4.2.0; extra == "all"
Requires-Dist: plotnine>=0.8.0; extra == "all"
Provides-Extra: dev
Requires-Dist: pytest>=6.0.0; extra == "dev"
Requires-Dist: pytest-cov>=2.0.0; extra == "dev"
Dynamic: license-file
